scaffold/__init__.py
scaffold/twork_admin.py
scaffold/twork_app/.bumpversion.cfg
scaffold/twork_app/.gitignore
scaffold/twork_app/Makefile
scaffold/twork_app/setup.py
scaffold/twork_app/tox.ini
scaffold/twork_app/conf/log.conf
scaffold/twork_app/conf/twork.conf
scaffold/twork_app/tests/test_heartbeat.py
scaffold/twork_app/tests/twork_env.py
scaffold/twork_app/tests/twork_test_base.py
scaffold/twork_app/twork_app/__init__.py
scaffold/twork_app/twork_app/constants.py
scaffold/twork_app/twork_app/errors.py
scaffold/twork_app/twork_app/module.py
scaffold/twork_app/twork_app/version.py
scaffold/twork_app/twork_app/app/__init__.py
scaffold/twork_app/twork_app/app/_setup.py
scaffold/twork_app/twork_app/app/handlers.py
scaffold/twork_app/twork_app/app/info.py
scaffold/twork_app/twork_app/app/options.py
scaffold/twork_app/twork_app/app/timer.py
scaffold/twork_app/twork_app/domain/__init__.py
scaffold/twork_app/twork_app/domain/bs/__init__.py
scaffold/twork_app/twork_app/domain/bs/base.py
scaffold/twork_app/twork_app/domain/dao/__init__.py
scaffold/twork_app/twork_app/domain/model/__init__.py
scaffold/twork_app/twork_app/libs/__init__.py
scaffold/twork_app/twork_app/utils/__init__.py
scaffold/twork_app/twork_app/web/__init__.py
scaffold/twork_app/twork_app/web/assembly.py
scaffold/twork_app/twork_app/web/action/__init__.py
scaffold/twork_app/twork_app/web/action/base.py
scaffold/twork_app/twork_app/web/action/health_check.py
scaffold/twork_app/twork_app/web/action/heartbeat.py
scaffold/twork_app/twork_app/web/action/not_found.py
scaffold/twork_app/twork_app/web/static/favicon.ico
scaffold/twork_app/twork_app/web/templates/README.md
twork/__init__.py
twork/assembly.py
twork/consts.py
twork/errors.py
twork/options.py
twork/tworkd.py
twork/domain/__init__.py
twork/timer/__init__.py
twork/timer/common_timer.py
twork/utils/__init__.py
twork/utils/common.py
twork/utils/log.py
twork/utils/object_likefy.py
twork/web/__init__.py
twork-2.0.14.dist-info/DESCRIPTION.rst
twork-2.0.14.dist-info/entry_points.txt
twork-2.0.14.dist-info/METADATA
twork-2.0.14.dist-info/metadata.json
twork-2.0.14.dist-info/RECORD
twork-2.0.14.dist-info/top_level.txt
twork-2.0.14.dist-info/WHEEL
