Metadata-Version: 2.0
Name: twork
Version: 2.0.14
Summary: twork is a Tornado Application FrameWork, it supports plug-in module injection, the module called TworkApp.
Home-page: https://github.com/bufferx/twork
Author: ZY Zhang
Author-email: idup2x@gmail.com
License: http://www.apache.org/licenses/LICENSE-2.0
Keywords: tornado,web framework,web server,server framework,twork
Platform: POSIX
Classifier: Intended Audience :: Developers
Classifier: License :: OSI Approved :: Apache Software License
Classifier: Operating System :: POSIX
Classifier: Programming Language :: Python
Requires-Dist: setproctitle (==1.1.8)
Requires-Dist: nose (==1.3.3)
Requires-Dist: tornado (==4.2.1)
Requires-Dist: psutil (==3.2.2)
